subash_chart_styles/__init__.py
subash_chart_styles/chart_styles.py
subash_chart_styles/config.py
subash_chart_styles/utils.py
tests/__init__.py
tests/test_chart_styles.py
subash_chart_styles-0.1.4.dist-info/METADATA
subash_chart_styles-0.1.4.dist-info/WHEEL
subash_chart_styles-0.1.4.dist-info/top_level.txt
subash_chart_styles-0.1.4.dist-info/RECORD
