Metadata-Version: 2.1
Name: subash_chart_styles
Version: 0.1.4
Summary: A Python package for generating styled market cap charts
Home-page: https://github.com/yourusername/subash_chart_styles
Author: Your Name
Author-email: your.email@example.com
Classifier: Programming Language :: Python :: 3
Classifier: License :: OSI Approved :: MIT License
Classifier: Operating System :: OS Independent
Requires-Python: >=3.6
Requires-Dist: matplotlib
Requires-Dist: psycopg2
Requires-Dist: slugify
